[
  {
    "timestamp": "2022-05-31T06:16:06.52093569Z",
    "schedulingLatency": 95,
    "initializedLatency": 228,
    "containersReadyLatency": 4827,
    "podReadyLatency": 4827,
    "metricName": "podLatencyMeasurement",
    "jobName": "api-intensive-create",
    "uuid": "9a88b996-d425-4b9a-a7a3-a4f9287055df",
    "namespace": "api-intensive-1",
    "podName": "api-intensive-2-8566549c7f-2c75s",
    "nodeName": "ip-10-23-214-89.eu-west-2.compute.internal"
  },
  {
    "timestamp": "2022-05-31T06:16:06.68407271Z",
    "schedulingLatency": 31,
    "initializedLatency": 102,
    "containersReadyLatency": 4630,
    "podReadyLatency": 4630,
    "metricName": "podLatencyMeasurement",
    "jobName": "api-intensive-create",
    "uuid": "9a88b996-d425-4b9a-a7a3-a4f9287055df",
    "namespace": "api-intensive-1",
    "podName": "api-intensive-1-79997588fc-mwm97",
    "nodeName": "ip-10-23-214-89.eu-west-2.compute.internal"
  },
  {
    "timestamp": "2022-05-31T06:22:36.222303984Z",
    "schedulingLatency": 27,
    "initializedLatency": 60,
    "containersReadyLatency": 2985,
    "podReadyLatency": 2985,
    "metricName": "podLatencyMeasurement",
    "jobName": "sdn-intensive",
    "uuid": "9a88b996-d425-4b9a-a7a3-a4f9287055df",
    "namespace": "sdn-intensive",
    "podName": "webserver-2-1-df7b478fd-m5mzv",
    "nodeName": "ip-10-23-214-89.eu-west-2.compute.internal"
  },
  {
    "timestamp": "2022-05-31T06:23:20.968787506Z",
    "schedulingLatency": 17,
    "initializedLatency": 79,
    "containersReadyLatency": 18665,
    "podReadyLatency": 18665,
    "metricName": "podLatencyMeasurement",
    "jobName": "cluster-intensive",
    "uuid": "9a88b996-d425-4b9a-a7a3-a4f9287055df",
    "namespace": "cluster-intensive-1",
    "podName": "deployment-1pod-2-5c657b9f85-z8bdf",
    "nodeName": "ip-10-23-218-28.eu-west-2.compute.internal"
  },
  {
    "timestamp": "2022-05-31T06:23:28.945518396Z",
    "schedulingLatency": 0,
    "initializedLatency": 132,
    "containersReadyLatency": 18434,
    "podReadyLatency": 18434,
    "metricName": "podLatencyMeasurement",
    "jobName": "cluster-intensive",
    "uuid": "9a88b996-d425-4b9a-a7a3-a4f9287055df",
    "namespace": "cluster-intensive-1",
    "podName": "deployment-1pod-1-6bc455ccd8-6wqd2",
    "nodeName": "ip-10-23-214-89.eu-west-2.compute.internal"
  },
  {
    "timestamp": "2022-05-31T06:23:28.946588008Z",
    "schedulingLatency": 145,
    "initializedLatency": 146,
    "containersReadyLatency": 18629,
    "podReadyLatency": 18629,
    "metricName": "podLatencyMeasurement",
    "jobName": "cluster-intensive",
    "uuid": "9a88b996-d425-4b9a-a7a3-a4f9287055df",
    "namespace": "cluster-intensive-1",
    "podName": "deployment-1pod-1-6bc455ccd8-rtk7l",
    "nodeName": "ip-10-23-218-28.eu-west-2.compute.internal"
  },
  {
    "timestamp": "2022-05-31T06:23:46.834629501Z",
    "schedulingLatency": 19,
    "initializedLatency": 63,
    "containersReadyLatency": 3555,
    "podReadyLatency": 3555,
    "metricName": "podLatencyMeasurement",
    "jobName": "cluster-intensive",
    "uuid": "9a88b996-d425-4b9a-a7a3-a4f9287055df",
    "namespace": "cluster-intensive-1",
    "podName": "deployment-2pod-1-76d9576b-hx7cc",
    "nodeName": "ip-10-23-214-89.eu-west-2.compute.internal"
  },
  {
    "timestamp": "2022-05-31T06:23:19.203671475Z",
    "schedulingLatency": 12,
    "initializedLatency": 62,
    "containersReadyLatency": 34190,
    "podReadyLatency": 34190,
    "metricName": "podLatencyMeasurement",
    "jobName": "cluster-intensive",
    "uuid": "9a88b996-d425-4b9a-a7a3-a4f9287055df",
    "namespace": "cluster-intensive-1",
    "podName": "deployment-2pod-2-7dc7b7f475-rdnwp",
    "nodeName": "ip-10-23-214-89.eu-west-2.compute.internal"
  },
  {
    "timestamp": "2022-05-31T06:23:20.921645647Z",
    "schedulingLatency": 0,
    "initializedLatency": 39,
    "containersReadyLatency": 18492,
    "podReadyLatency": 18492,
    "metricName": "podLatencyMeasurement",
    "jobName": "cluster-intensive",
    "uuid": "9a88b996-d425-4b9a-a7a3-a4f9287055df",
    "namespace": "cluster-intensive-1",
    "podName": "deployment-1pod-2-5c657b9f85-xdn8g",
    "nodeName": "ip-10-23-214-89.eu-west-2.compute.internal"
  },
  {
    "timestamp": "2022-05-31T06:23:46.040602762Z",
    "schedulingLatency": 44,
    "initializedLatency": 16537,
    "containersReadyLatency": 17692,
    "podReadyLatency": 17692,
    "metricName": "podLatencyMeasurement",
    "jobName": "cluster-intensive",
    "uuid": "9a88b996-d425-4b9a-a7a3-a4f9287055df",
    "namespace": "cluster-intensive-1",
    "podName": "cluster-intensive-1-1-build",
    "nodeName": "ip-10-23-214-89.eu-west-2.compute.internal"
  },
  {
    "timestamp": "2022-05-31T06:23:46.902575472Z",
    "schedulingLatency": 97,
    "initializedLatency": 113,
    "containersReadyLatency": 2674,
    "podReadyLatency": 2674,
    "metricName": "podLatencyMeasurement",
    "jobName": "cluster-intensive",
    "uuid": "9a88b996-d425-4b9a-a7a3-a4f9287055df",
    "namespace": "cluster-intensive-1",
    "podName": "deployment-2pod-1-76d9576b-n6nwt",
    "nodeName": "ip-10-23-218-28.eu-west-2.compute.internal"
  },
  {
    "timestamp": "2022-05-31T06:23:19.549747579Z",
    "schedulingLatency": 33,
    "initializedLatency": 93,
    "containersReadyLatency": 34039,
    "podReadyLatency": 34039,
    "metricName": "podLatencyMeasurement",
    "jobName": "cluster-intensive",
    "uuid": "9a88b996-d425-4b9a-a7a3-a4f9287055df",
    "namespace": "cluster-intensive-1",
    "podName": "deployment-2pod-2-7dc7b7f475-9fj4p",
    "nodeName": "ip-10-23-218-28.eu-west-2.compute.internal"
  },
  {
    "timestamp": "2022-05-31T06:23:44.444142201Z",
    "schedulingLatency": 29,
    "initializedLatency": 15116,
    "containersReadyLatency": 16139,
    "podReadyLatency": 16139,
    "metricName": "podLatencyMeasurement",
    "jobName": "cluster-intensive",
    "uuid": "9a88b996-d425-4b9a-a7a3-a4f9287055df",
    "namespace": "cluster-intensive-1",
    "podName": "cluster-intensive-1-build",
    "nodeName": "ip-10-23-214-89.eu-west-2.compute.internal"
  }
]
