[{"timestamp":"2022-05-26T08:01:38.323Z","labels":{"condition":"DiskPressure"},"value":0,"uuid":"efc41645-cb75-4dfa-acbe-beffdad1c0bf","query":"sum(kube_node_status_condition{status=\"true\"}) by (condition)","metricName":"nodeStatus","jobName":"cluster-density"},{"timestamp":"2022-05-26T08:02:08.323Z","labels":{"condition":"DiskPressure"},"value":0,"uuid":"efc41645-cb75-4dfa-acbe-beffdad1c0bf","query":"sum(kube_node_status_condition{status=\"true\"}) by (condition)","metricName":"nodeStatus","jobName":"cluster-density"},{"timestamp":"2022-05-26T08:02:38.323Z","labels":{"condition":"DiskPressure"},"value":0,"uuid":"efc41645-cb75-4dfa-acbe-beffdad1c0bf","query":"sum(kube_node_status_condition{status=\"true\"}) by (condition)","metricName":"nodeStatus","jobName":"cluster-density"},{"timestamp":"2022-05-26T08:03:08.323Z","labels":{"condition":"DiskPressure"},"value":0,"uuid":"efc41645-cb75-4dfa-acbe-beffdad1c0bf","query":"sum(kube_node_status_condition{status=\"true\"}) by (condition)","metricName":"nodeStatus","jobName":"cluster-density"},{"timestamp":"2022-05-26T08:03:38.323Z","labels":{"condition":"DiskPressure"},"value":0,"uuid":"efc41645-cb75-4dfa-acbe-beffdad1c0bf","query":"sum(kube_node_status_condition{status=\"true\"}) by (condition)","metricName":"nodeStatus","jobName":"cluster-density"},{"timestamp":"2022-05-26T08:04:08.323Z","labels":{"condition":"DiskPressure"},"value":0,"uuid":"efc41645-cb75-4dfa-acbe-beffdad1c0bf","query":"sum(kube_node_status_condition{status=\"true\"}) by (condition)","metricName":"nodeStatus","jobName":"cluster-density"},{"timestamp":"2022-05-26T08:01:38.323Z","labels":{"condition":"MemoryPressure"},"value":0,"uuid":"efc41645-cb75-4dfa-acbe-beffdad1c0bf","query":"sum(kube_node_status_condition{status=\"true\"}) by (condition)","metricName":"nodeStatus","jobName":"cluster-density"},{"timestamp":"2022-05-26T08:02:08.323Z","labels":{"condition":"MemoryPressure"},"value":0,"uuid":"efc41645-cb75-4dfa-acbe-beffdad1c0bf","query":"sum(kube_node_status_condition{status=\"true\"}) by (condition)","metricName":"nodeStatus","jobName":"cluster-density"},{"timestamp":"2022-05-26T08:02:38.323Z","labels":{"condition":"MemoryPressure"},"value":0,"uuid":"efc41645-cb75-4dfa-acbe-beffdad1c0bf","query":"sum(kube_node_status_condition{status=\"true\"}) by (condition)","metricName":"nodeStatus","jobName":"cluster-density"},{"timestamp":"2022-05-26T08:03:08.323Z","labels":{"condition":"MemoryPressure"},"value":0,"uuid":"efc41645-cb75-4dfa-acbe-beffdad1c0bf","query":"sum(kube_node_status_condition{status=\"true\"}) by (condition)","metricName":"nodeStatus","jobName":"cluster-density"},{"timestamp":"2022-05-26T08:03:38.323Z","labels":{"condition":"MemoryPressure"},"value":0,"uuid":"efc41645-cb75-4dfa-acbe-beffdad1c0bf","query":"sum(kube_node_status_condition{status=\"true\"}) by (condition)","metricName":"nodeStatus","jobName":"cluster-density"},{"timestamp":"2022-05-26T08:04:08.323Z","labels":{"condition":"MemoryPressure"},"value":0,"uuid":"efc41645-cb75-4dfa-acbe-beffdad1c0bf","query":"sum(kube_node_status_condition{status=\"true\"}) by (condition)","metricName":"nodeStatus","jobName":"cluster-density"},{"timestamp":"2022-05-26T08:01:38.323Z","labels":{"condition":"PIDPressure"},"value":0,"uuid":"efc41645-cb75-4dfa-acbe-beffdad1c0bf","query":"sum(kube_node_status_condition{status=\"true\"}) by (condition)","metricName":"nodeStatus","jobName":"cluster-density"},{"timestamp":"2022-05-26T08:02:08.323Z","labels":{"condition":"PIDPressure"},"value":0,"uuid":"efc41645-cb75-4dfa-acbe-beffdad1c0bf","query":"sum(kube_node_status_condition{status=\"true\"}) by (condition)","metricName":"nodeStatus","jobName":"cluster-density"},{"timestamp":"2022-05-26T08:02:38.323Z","labels":{"condition":"PIDPressure"},"value":0,"uuid":"efc41645-cb75-4dfa-acbe-beffdad1c0bf","query":"sum(kube_node_status_condition{status=\"true\"}) by (condition)","metricName":"nodeStatus","jobName":"cluster-density"},{"timestamp":"2022-05-26T08:03:08.323Z","labels":{"condition":"PIDPressure"},"value":0,"uuid":"efc41645-cb75-4dfa-acbe-beffdad1c0bf","query":"sum(kube_node_status_condition{status=\"true\"}) by (condition)","metricName":"nodeStatus","jobName":"cluster-density"},{"timestamp":"2022-05-26T08:03:38.323Z","labels":{"condition":"PIDPressure"},"value":0,"uuid":"efc41645-cb75-4dfa-acbe-beffdad1c0bf","query":"sum(kube_node_status_condition{status=\"true\"}) by (condition)","metricName":"nodeStatus","jobName":"cluster-density"},{"timestamp":"2022-05-26T08:04:08.323Z","labels":{"condition":"PIDPressure"},"value":0,"uuid":"efc41645-cb75-4dfa-acbe-beffdad1c0bf","query":"sum(kube_node_status_condition{status=\"true\"}) by (condition)","metricName":"nodeStatus","jobName":"cluster-density"},{"timestamp":"2022-05-26T08:01:38.323Z","labels":{"condition":"Ready"},"value":6,"uuid":"efc41645-cb75-4dfa-acbe-beffdad1c0bf","query":"sum(kube_node_status_condition{status=\"true\"}) by (condition)","metricName":"nodeStatus","jobName":"cluster-density"},{"timestamp":"2022-05-26T08:02:08.323Z","labels":{"condition":"Ready"},"value":6,"uuid":"efc41645-cb75-4dfa-acbe-beffdad1c0bf","query":"sum(kube_node_status_condition{status=\"true\"}) by (condition)","metricName":"nodeStatus","jobName":"cluster-density"},{"timestamp":"2022-05-26T08:02:38.323Z","labels":{"condition":"Ready"},"value":6,"uuid":"efc41645-cb75-4dfa-acbe-beffdad1c0bf","query":"sum(kube_node_status_condition{status=\"true\"}) by (condition)","metricName":"nodeStatus","jobName":"cluster-density"},{"timestamp":"2022-05-26T08:03:08.323Z","labels":{"condition":"Ready"},"value":6,"uuid":"efc41645-cb75-4dfa-acbe-beffdad1c0bf","query":"sum(kube_node_status_condition{status=\"true\"}) by (condition)","metricName":"nodeStatus","jobName":"cluster-density"},{"timestamp":"2022-05-26T08:03:38.323Z","labels":{"condition":"Ready"},"value":6,"uuid":"efc41645-cb75-4dfa-acbe-beffdad1c0bf","query":"sum(kube_node_status_condition{status=\"true\"}) by (condition)","metricName":"nodeStatus","jobName":"cluster-density"},{"timestamp":"2022-05-26T08:04:08.323Z","labels":{"condition":"Ready"},"value":6,"uuid":"efc41645-cb75-4dfa-acbe-beffdad1c0bf","query":"sum(kube_node_status_condition{status=\"true\"}) by (condition)","metricName":"nodeStatus","jobName":"cluster-density"}]
