[{"timestamp":"2022-05-26T06:44:09.436Z","labels":{"device":"sda"},"value":31844.774603174603,"uuid":"7353d0de-dbde-43d8-a98b-217b4d6ddf82","query":"avg(rate(node_disk_written_bytes_total{device!~\"^(dm|rb).*\"}[2m]) and on (instance) label_replace(kube_node_role{role=\"worker\"}, \"instance\", \"$1\", \"node\", \"(.+)\")) by (device)","metricName":"nodeDiskWrittenBytes-AggregatedWorkers","jobName":"cluster-density"},{"timestamp":"2022-05-26T06:44:39.436Z","labels":{"device":"sda"},"value":1619457.6253968251,"uuid":"7353d0de-dbde-43d8-a98b-217b4d6ddf82","query":"avg(rate(node_disk_written_bytes_total{device!~\"^(dm|rb).*\"}[2m]) and on (instance) label_replace(kube_node_role{role=\"worker\"}, \"instance\", \"$1\", \"node\", \"(.+)\")) by (device)","metricName":"nodeDiskWrittenBytes-AggregatedWorkers","jobName":"cluster-density"},{"timestamp":"2022-05-26T06:45:09.436Z","labels":{"device":"sda"},"value":12668321.726984128,"uuid":"7353d0de-dbde-43d8-a98b-217b4d6ddf82","query":"avg(rate(node_disk_written_bytes_total{device!~\"^(dm|rb).*\"}[2m]) and on (instance) label_replace(kube_node_role{role=\"worker\"}, \"instance\", \"$1\", \"node\", \"(.+)\")) by (device)","metricName":"nodeDiskWrittenBytes-AggregatedWorkers","jobName":"cluster-density"},{"timestamp":"2022-05-26T06:45:39.436Z","labels":{"device":"sda"},"value":21193820.647619046,"uuid":"7353d0de-dbde-43d8-a98b-217b4d6ddf82","query":"avg(rate(node_disk_written_bytes_total{device!~\"^(dm|rb).*\"}[2m]) and on (instance) label_replace(kube_node_role{role=\"worker\"}, \"instance\", \"$1\", \"node\", \"(.+)\")) by (device)","metricName":"nodeDiskWrittenBytes-AggregatedWorkers","jobName":"cluster-density"},{"timestamp":"2022-05-26T06:46:09.436Z","labels":{"device":"sda"},"value":30010522.412698414,"uuid":"7353d0de-dbde-43d8-a98b-217b4d6ddf82","query":"avg(rate(node_disk_written_bytes_total{device!~\"^(dm|rb).*\"}[2m]) and on (instance) label_replace(kube_node_role{role=\"worker\"}, \"instance\", \"$1\", \"node\", \"(.+)\")) by (device)","metricName":"nodeDiskWrittenBytes-AggregatedWorkers","jobName":"cluster-density"},{"timestamp":"2022-05-26T06:46:39.436Z","labels":{"device":"sda"},"value":28394726.806349203,"uuid":"7353d0de-dbde-43d8-a98b-217b4d6ddf82","query":"avg(rate(node_disk_written_bytes_total{device!~\"^(dm|rb).*\"}[2m]) and on (instance) label_replace(kube_node_role{role=\"worker\"}, \"instance\", \"$1\", \"node\", \"(.+)\")) by (device)","metricName":"nodeDiskWrittenBytes-AggregatedWorkers","jobName":"cluster-density"},{"timestamp":"2022-05-26T06:44:09.436Z","labels":{"device":"sdb"},"value":150901.84126984127,"uuid":"7353d0de-dbde-43d8-a98b-217b4d6ddf82","query":"avg(rate(node_disk_written_bytes_total{device!~\"^(dm|rb).*\"}[2m]) and on (instance) label_replace(kube_node_role{role=\"worker\"}, \"instance\", \"$1\", \"node\", \"(.+)\")) by (device)","metricName":"nodeDiskWrittenBytes-AggregatedWorkers","jobName":"cluster-density"},{"timestamp":"2022-05-26T06:44:39.436Z","labels":{"device":"sdb"},"value":2564905.4476190475,"uuid":"7353d0de-dbde-43d8-a98b-217b4d6ddf82","query":"avg(rate(node_disk_written_bytes_total{device!~\"^(dm|rb).*\"}[2m]) and on (instance) label_replace(kube_node_role{role=\"worker\"}, \"instance\", \"$1\", \"node\", \"(.+)\")) by (device)","metricName":"nodeDiskWrittenBytes-AggregatedWorkers","jobName":"cluster-density"},{"timestamp":"2022-05-26T06:45:09.436Z","labels":{"device":"sdb"},"value":20059177.80993035,"uuid":"7353d0de-dbde-43d8-a98b-217b4d6ddf82","query":"avg(rate(node_disk_written_bytes_total{device!~\"^(dm|rb).*\"}[2m]) and on (instance) label_replace(kube_node_role{role=\"worker\"}, \"instance\", \"$1\", \"node\", \"(.+)\")) by (device)","metricName":"nodeDiskWrittenBytes-AggregatedWorkers","jobName":"cluster-density"},{"timestamp":"2022-05-26T06:45:39.436Z","labels":{"device":"sdb"},"value":28631625.849574298,"uuid":"7353d0de-dbde-43d8-a98b-217b4d6ddf82","query":"avg(rate(node_disk_written_bytes_total{device!~\"^(dm|rb).*\"}[2m]) and on (instance) label_replace(kube_node_role{role=\"worker\"}, \"instance\", \"$1\", \"node\", \"(.+)\")) by (device)","metricName":"nodeDiskWrittenBytes-AggregatedWorkers","jobName":"cluster-density"},{"timestamp":"2022-05-26T06:46:09.436Z","labels":{"device":"sdb"},"value":36571453.05848012,"uuid":"7353d0de-dbde-43d8-a98b-217b4d6ddf82","query":"avg(rate(node_disk_written_bytes_total{device!~\"^(dm|rb).*\"}[2m]) and on (instance) label_replace(kube_node_role{role=\"worker\"}, \"instance\", \"$1\", \"node\", \"(.+)\")) by (device)","metricName":"nodeDiskWrittenBytes-AggregatedWorkers","jobName":"cluster-density"},{"timestamp":"2022-05-26T06:46:39.436Z","labels":{"device":"sdb"},"value":28465300.22026301,"uuid":"7353d0de-dbde-43d8-a98b-217b4d6ddf82","query":"avg(rate(node_disk_written_bytes_total{device!~\"^(dm|rb).*\"}[2m]) and on (instance) label_replace(kube_node_role{role=\"worker\"}, \"instance\", \"$1\", \"node\", \"(.+)\")) by (device)","metricName":"nodeDiskWrittenBytes-AggregatedWorkers","jobName":"cluster-density"},{"timestamp":"2022-05-26T06:44:09.436Z","labels":{"device":"sdc"},"value":420340.6222222222,"uuid":"7353d0de-dbde-43d8-a98b-217b4d6ddf82","query":"avg(rate(node_disk_written_bytes_total{device!~\"^(dm|rb).*\"}[2m]) and on (instance) label_replace(kube_node_role{role=\"worker\"}, \"instance\", \"$1\", \"node\", \"(.+)\")) by (device)","metricName":"nodeDiskWrittenBytes-AggregatedWorkers","jobName":"cluster-density"},{"timestamp":"2022-05-26T06:44:39.436Z","labels":{"device":"sdc"},"value":625426.6920634921,"uuid":"7353d0de-dbde-43d8-a98b-217b4d6ddf82","query":"avg(rate(node_disk_written_bytes_total{device!~\"^(dm|rb).*\"}[2m]) and on (instance) label_replace(kube_node_role{role=\"worker\"}, \"instance\", \"$1\", \"node\", \"(.+)\")) by (device)","metricName":"nodeDiskWrittenBytes-AggregatedWorkers","jobName":"cluster-density"},{"timestamp":"2022-05-26T06:45:09.436Z","labels":{"device":"sdc"},"value":784892.579649396,"uuid":"7353d0de-dbde-43d8-a98b-217b4d6ddf82","query":"avg(rate(node_disk_written_bytes_total{device!~\"^(dm|rb).*\"}[2m]) and on (instance) label_replace(kube_node_role{role=\"worker\"}, \"instance\", \"$1\", \"node\", \"(.+)\")) by (device)","metricName":"nodeDiskWrittenBytes-AggregatedWorkers","jobName":"cluster-density"},{"timestamp":"2022-05-26T06:45:39.436Z","labels":{"device":"sdc"},"value":925044.363554732,"uuid":"7353d0de-dbde-43d8-a98b-217b4d6ddf82","query":"avg(rate(node_disk_written_bytes_total{device!~\"^(dm|rb).*\"}[2m]) and on (instance) label_replace(kube_node_role{role=\"worker\"}, \"instance\", \"$1\", \"node\", \"(.+)\")) by (device)","metricName":"nodeDiskWrittenBytes-AggregatedWorkers","jobName":"cluster-density"},{"timestamp":"2022-05-26T06:46:09.436Z","labels":{"device":"sdc"},"value":897933.3921194936,"uuid":"7353d0de-dbde-43d8-a98b-217b4d6ddf82","query":"avg(rate(node_disk_written_bytes_total{device!~\"^(dm|rb).*\"}[2m]) and on (instance) label_replace(kube_node_role{role=\"worker\"}, \"instance\", \"$1\", \"node\", \"(.+)\")) by (device)","metricName":"nodeDiskWrittenBytes-AggregatedWorkers","jobName":"cluster-density"},{"timestamp":"2022-05-26T06:46:39.436Z","labels":{"device":"sdc"},"value":771518.651752693,"uuid":"7353d0de-dbde-43d8-a98b-217b4d6ddf82","query":"avg(rate(node_disk_written_bytes_total{device!~\"^(dm|rb).*\"}[2m]) and on (instance) label_replace(kube_node_role{role=\"worker\"}, \"instance\", \"$1\", \"node\", \"(.+)\")) by (device)","metricName":"nodeDiskWrittenBytes-AggregatedWorkers","jobName":"cluster-density"},{"timestamp":"2022-05-26T06:44:09.436Z","labels":{"device":"sdd"},"value":975.2380952380952,"uuid":"7353d0de-dbde-43d8-a98b-217b4d6ddf82","query":"avg(rate(node_disk_written_bytes_total{device!~\"^(dm|rb).*\"}[2m]) and on (instance) label_replace(kube_node_role{role=\"worker\"}, \"instance\", \"$1\", \"node\", \"(.+)\")) by (device)","metricName":"nodeDiskWrittenBytes-AggregatedWorkers","jobName":"cluster-density"},{"timestamp":"2022-05-26T06:44:39.436Z","labels":{"device":"sdd"},"value":975.2380952380952,"uuid":"7353d0de-dbde-43d8-a98b-217b4d6ddf82","query":"avg(rate(node_disk_written_bytes_total{device!~\"^(dm|rb).*\"}[2m]) and on (instance) label_replace(kube_node_role{role=\"worker\"}, \"instance\", \"$1\", \"node\", \"(.+)\")) by (device)","metricName":"nodeDiskWrittenBytes-AggregatedWorkers","jobName":"cluster-density"},{"timestamp":"2022-05-26T06:45:09.436Z","labels":{"device":"sdd"},"value":975.2659599798088,"uuid":"7353d0de-dbde-43d8-a98b-217b4d6ddf82","query":"avg(rate(node_disk_written_bytes_total{device!~\"^(dm|rb).*\"}[2m]) and on (instance) label_replace(kube_node_role{role=\"worker\"}, \"instance\", \"$1\", \"node\", \"(.+)\")) by (device)","metricName":"nodeDiskWrittenBytes-AggregatedWorkers","jobName":"cluster-density"},{"timestamp":"2022-05-26T06:45:39.436Z","labels":{"device":"sdd"},"value":975.3588539533467,"uuid":"7353d0de-dbde-43d8-a98b-217b4d6ddf82","query":"avg(rate(node_disk_written_bytes_total{device!~\"^(dm|rb).*\"}[2m]) and on (instance) label_replace(kube_node_role{role=\"worker\"}, \"instance\", \"$1\", \"node\", \"(.+)\")) by (device)","metricName":"nodeDiskWrittenBytes-AggregatedWorkers","jobName":"cluster-density"},{"timestamp":"2022-05-26T06:46:09.436Z","labels":{"device":"sdd"},"value":975.2752485808984,"uuid":"7353d0de-dbde-43d8-a98b-217b4d6ddf82","query":"avg(rate(node_disk_written_bytes_total{device!~\"^(dm|rb).*\"}[2m]) and on (instance) label_replace(kube_node_role{role=\"worker\"}, \"instance\", \"$1\", \"node\", \"(.+)\")) by (device)","metricName":"nodeDiskWrittenBytes-AggregatedWorkers","jobName":"cluster-density"},{"timestamp":"2022-05-26T06:46:39.436Z","labels":{"device":"sdd"},"value":975.3402737429635,"uuid":"7353d0de-dbde-43d8-a98b-217b4d6ddf82","query":"avg(rate(node_disk_written_bytes_total{device!~\"^(dm|rb).*\"}[2m]) and on (instance) label_replace(kube_node_role{role=\"worker\"}, \"instance\", \"$1\", \"node\", \"(.+)\")) by (device)","metricName":"nodeDiskWrittenBytes-AggregatedWorkers","jobName":"cluster-density"},{"timestamp":"2022-05-26T06:44:09.436Z","labels":{"device":"sr0"},"value":0,"uuid":"7353d0de-dbde-43d8-a98b-217b4d6ddf82","query":"avg(rate(node_disk_written_bytes_total{device!~\"^(dm|rb).*\"}[2m]) and on (instance) label_replace(kube_node_role{role=\"worker\"}, \"instance\", \"$1\", \"node\", \"(.+)\")) by (device)","metricName":"nodeDiskWrittenBytes-AggregatedWorkers","jobName":"cluster-density"},{"timestamp":"2022-05-26T06:44:39.436Z","labels":{"device":"sr0"},"value":0,"uuid":"7353d0de-dbde-43d8-a98b-217b4d6ddf82","query":"avg(rate(node_disk_written_bytes_total{device!~\"^(dm|rb).*\"}[2m]) and on (instance) label_replace(kube_node_role{role=\"worker\"}, \"instance\", \"$1\", \"node\", \"(.+)\")) by (device)","metricName":"nodeDiskWrittenBytes-AggregatedWorkers","jobName":"cluster-density"},{"timestamp":"2022-05-26T06:45:09.436Z","labels":{"device":"sr0"},"value":0,"uuid":"7353d0de-dbde-43d8-a98b-217b4d6ddf82","query":"avg(rate(node_disk_written_bytes_total{device!~\"^(dm|rb).*\"}[2m]) and on (instance) label_replace(kube_node_role{role=\"worker\"}, \"instance\", \"$1\", \"node\", \"(.+)\")) by (device)","metricName":"nodeDiskWrittenBytes-AggregatedWorkers","jobName":"cluster-density"},{"timestamp":"2022-05-26T06:45:39.436Z","labels":{"device":"sr0"},"value":0,"uuid":"7353d0de-dbde-43d8-a98b-217b4d6ddf82","query":"avg(rate(node_disk_written_bytes_total{device!~\"^(dm|rb).*\"}[2m]) and on (instance) label_replace(kube_node_role{role=\"worker\"}, \"instance\", \"$1\", \"node\", \"(.+)\")) by (device)","metricName":"nodeDiskWrittenBytes-AggregatedWorkers","jobName":"cluster-density"},{"timestamp":"2022-05-26T06:46:09.436Z","labels":{"device":"sr0"},"value":0,"uuid":"7353d0de-dbde-43d8-a98b-217b4d6ddf82","query":"avg(rate(node_disk_written_bytes_total{device!~\"^(dm|rb).*\"}[2m]) and on (instance) label_replace(kube_node_role{role=\"worker\"}, \"instance\", \"$1\", \"node\", \"(.+)\")) by (device)","metricName":"nodeDiskWrittenBytes-AggregatedWorkers","jobName":"cluster-density"},{"timestamp":"2022-05-26T06:46:39.436Z","labels":{"device":"sr0"},"value":0,"uuid":"7353d0de-dbde-43d8-a98b-217b4d6ddf82","query":"avg(rate(node_disk_written_bytes_total{device!~\"^(dm|rb).*\"}[2m]) and on (instance) label_replace(kube_node_role{role=\"worker\"}, \"instance\", \"$1\", \"node\", \"(.+)\")) by (device)","metricName":"nodeDiskWrittenBytes-AggregatedWorkers","jobName":"cluster-density"}]
