[{"timestamp":"2022-05-26T06:44:09.436Z","labels":{"apiserver":"kube-apiserver","operation":"create"},"value":0.0858181818181818,"uuid":"7353d0de-dbde-43d8-a98b-217b4d6ddf82","query":"histogram_quantile(0.99,sum(rate(etcd_request_duration_seconds_bucket[2m])) by (le,operation,apiserver)) \u003e 0","metricName":"P99APIEtcdRequestLatency","jobName":"cluster-density"},{"timestamp":"2022-05-26T06:44:39.436Z","labels":{"apiserver":"kube-apiserver","operation":"create"},"value":0.09478628869011296,"uuid":"7353d0de-dbde-43d8-a98b-217b4d6ddf82","query":"histogram_quantile(0.99,sum(rate(etcd_request_duration_seconds_bucket[2m])) by (le,operation,apiserver)) \u003e 0","metricName":"P99APIEtcdRequestLatency","jobName":"cluster-density"},{"timestamp":"2022-05-26T06:45:09.436Z","labels":{"apiserver":"kube-apiserver","operation":"create"},"value":0.09458620797994136,"uuid":"7353d0de-dbde-43d8-a98b-217b4d6ddf82","query":"histogram_quantile(0.99,sum(rate(etcd_request_duration_seconds_bucket[2m])) by (le,operation,apiserver)) \u003e 0","metricName":"P99APIEtcdRequestLatency","jobName":"cluster-density"},{"timestamp":"2022-05-26T06:45:39.436Z","labels":{"apiserver":"kube-apiserver","operation":"create"},"value":0.09414325842696633,"uuid":"7353d0de-dbde-43d8-a98b-217b4d6ddf82","query":"histogram_quantile(0.99,sum(rate(etcd_request_duration_seconds_bucket[2m])) by (le,operation,apiserver)) \u003e 0","metricName":"P99APIEtcdRequestLatency","jobName":"cluster-density"},{"timestamp":"2022-05-26T06:46:09.436Z","labels":{"apiserver":"kube-apiserver","operation":"create"},"value":0.09084615384615385,"uuid":"7353d0de-dbde-43d8-a98b-217b4d6ddf82","query":"histogram_quantile(0.99,sum(rate(etcd_request_duration_seconds_bucket[2m])) by (le,operation,apiserver)) \u003e 0","metricName":"P99APIEtcdRequestLatency","jobName":"cluster-density"},{"timestamp":"2022-05-26T06:46:39.436Z","labels":{"apiserver":"kube-apiserver","operation":"create"},"value":0.0833269230769232,"uuid":"7353d0de-dbde-43d8-a98b-217b4d6ddf82","query":"histogram_quantile(0.99,sum(rate(etcd_request_duration_seconds_bucket[2m])) by (le,operation,apiserver)) \u003e 0","metricName":"P99APIEtcdRequestLatency","jobName":"cluster-density"},{"timestamp":"2022-05-26T06:44:09.436Z","labels":{"apiserver":"kube-apiserver","operation":"delete"},"value":0.06700000000000006,"uuid":"7353d0de-dbde-43d8-a98b-217b4d6ddf82","query":"histogram_quantile(0.99,sum(rate(etcd_request_duration_seconds_bucket[2m])) by (le,operation,apiserver)) \u003e 0","metricName":"P99APIEtcdRequestLatency","jobName":"cluster-density"},{"timestamp":"2022-05-26T06:44:39.436Z","labels":{"apiserver":"kube-apiserver","operation":"delete"},"value":0.08387500000000002,"uuid":"7353d0de-dbde-43d8-a98b-217b4d6ddf82","query":"histogram_quantile(0.99,sum(rate(etcd_request_duration_seconds_bucket[2m])) by (le,operation,apiserver)) \u003e 0","metricName":"P99APIEtcdRequestLatency","jobName":"cluster-density"},{"timestamp":"2022-05-26T06:45:09.436Z","labels":{"apiserver":"kube-apiserver","operation":"delete"},"value":0.08762500000000009,"uuid":"7353d0de-dbde-43d8-a98b-217b4d6ddf82","query":"histogram_quantile(0.99,sum(rate(etcd_request_duration_seconds_bucket[2m])) by (le,operation,apiserver)) \u003e 0","metricName":"P99APIEtcdRequestLatency","jobName":"cluster-density"},{"timestamp":"2022-05-26T06:45:39.436Z","labels":{"apiserver":"kube-apiserver","operation":"delete"},"value":0.08499999999999985,"uuid":"7353d0de-dbde-43d8-a98b-217b4d6ddf82","query":"histogram_quantile(0.99,sum(rate(etcd_request_duration_seconds_bucket[2m])) by (le,operation,apiserver)) \u003e 0","metricName":"P99APIEtcdRequestLatency","jobName":"cluster-density"},{"timestamp":"2022-05-26T06:46:09.436Z","labels":{"apiserver":"kube-apiserver","operation":"delete"},"value":0.024691666666666667,"uuid":"7353d0de-dbde-43d8-a98b-217b4d6ddf82","query":"histogram_quantile(0.99,sum(rate(etcd_request_duration_seconds_bucket[2m])) by (le,operation,apiserver)) \u003e 0","metricName":"P99APIEtcdRequestLatency","jobName":"cluster-density"},{"timestamp":"2022-05-26T06:46:39.436Z","labels":{"apiserver":"kube-apiserver","operation":"delete"},"value":0.024716129032258068,"uuid":"7353d0de-dbde-43d8-a98b-217b4d6ddf82","query":"histogram_quantile(0.99,sum(rate(etcd_request_duration_seconds_bucket[2m])) by (le,operation,apiserver)) \u003e 0","metricName":"P99APIEtcdRequestLatency","jobName":"cluster-density"},{"timestamp":"2022-05-26T06:44:09.436Z","labels":{"apiserver":"kube-apiserver","operation":"get"},"value":0.02449280910501808,"uuid":"7353d0de-dbde-43d8-a98b-217b4d6ddf82","query":"histogram_quantile(0.99,sum(rate(etcd_request_duration_seconds_bucket[2m])) by (le,operation,apiserver)) \u003e 0","metricName":"P99APIEtcdRequestLatency","jobName":"cluster-density"},{"timestamp":"2022-05-26T06:44:39.436Z","labels":{"apiserver":"kube-apiserver","operation":"get"},"value":0.0819304741067349,"uuid":"7353d0de-dbde-43d8-a98b-217b4d6ddf82","query":"histogram_quantile(0.99,sum(rate(etcd_request_duration_seconds_bucket[2m])) by (le,operation,apiserver)) \u003e 0","metricName":"P99APIEtcdRequestLatency","jobName":"cluster-density"},{"timestamp":"2022-05-26T06:45:09.436Z","labels":{"apiserver":"kube-apiserver","operation":"get"},"value":0.08873109509264532,"uuid":"7353d0de-dbde-43d8-a98b-217b4d6ddf82","query":"histogram_quantile(0.99,sum(rate(etcd_request_duration_seconds_bucket[2m])) by (le,operation,apiserver)) \u003e 0","metricName":"P99APIEtcdRequestLatency","jobName":"cluster-density"},{"timestamp":"2022-05-26T06:45:39.436Z","labels":{"apiserver":"kube-apiserver","operation":"get"},"value":0.08992105263157915,"uuid":"7353d0de-dbde-43d8-a98b-217b4d6ddf82","query":"histogram_quantile(0.99,sum(rate(etcd_request_duration_seconds_bucket[2m])) by (le,operation,apiserver)) \u003e 0","metricName":"P99APIEtcdRequestLatency","jobName":"cluster-density"},{"timestamp":"2022-05-26T06:46:09.436Z","labels":{"apiserver":"kube-apiserver","operation":"get"},"value":0.0779038461538461,"uuid":"7353d0de-dbde-43d8-a98b-217b4d6ddf82","query":"histogram_quantile(0.99,sum(rate(etcd_request_duration_seconds_bucket[2m])) by (le,operation,apiserver)) \u003e 0","metricName":"P99APIEtcdRequestLatency","jobName":"cluster-density"},{"timestamp":"2022-05-26T06:46:39.436Z","labels":{"apiserver":"kube-apiserver","operation":"get"},"value":0.02490514469453376,"uuid":"7353d0de-dbde-43d8-a98b-217b4d6ddf82","query":"histogram_quantile(0.99,sum(rate(etcd_request_duration_seconds_bucket[2m])) by (le,operation,apiserver)) \u003e 0","metricName":"P99APIEtcdRequestLatency","jobName":"cluster-density"},{"timestamp":"2022-05-26T06:44:09.436Z","labels":{"apiserver":"kube-apiserver","operation":"list"},"value":0.028750000000000525,"uuid":"7353d0de-dbde-43d8-a98b-217b4d6ddf82","query":"histogram_quantile(0.99,sum(rate(etcd_request_duration_seconds_bucket[2m])) by (le,operation,apiserver)) \u003e 0","metricName":"P99APIEtcdRequestLatency","jobName":"cluster-density"},{"timestamp":"2022-05-26T06:44:39.436Z","labels":{"apiserver":"kube-apiserver","operation":"list"},"value":0.09473025592081138,"uuid":"7353d0de-dbde-43d8-a98b-217b4d6ddf82","query":"histogram_quantile(0.99,sum(rate(etcd_request_duration_seconds_bucket[2m])) by (le,operation,apiserver)) \u003e 0","metricName":"P99APIEtcdRequestLatency","jobName":"cluster-density"},{"timestamp":"2022-05-26T06:45:09.436Z","labels":{"apiserver":"kube-apiserver","operation":"list"},"value":0.09652269367672894,"uuid":"7353d0de-dbde-43d8-a98b-217b4d6ddf82","query":"histogram_quantile(0.99,sum(rate(etcd_request_duration_seconds_bucket[2m])) by (le,operation,apiserver)) \u003e 0","metricName":"P99APIEtcdRequestLatency","jobName":"cluster-density"},{"timestamp":"2022-05-26T06:45:39.436Z","labels":{"apiserver":"kube-apiserver","operation":"list"},"value":0.09647499999999992,"uuid":"7353d0de-dbde-43d8-a98b-217b4d6ddf82","query":"histogram_quantile(0.99,sum(rate(etcd_request_duration_seconds_bucket[2m])) by (le,operation,apiserver)) \u003e 0","metricName":"P99APIEtcdRequestLatency","jobName":"cluster-density"},{"timestamp":"2022-05-26T06:46:09.436Z","labels":{"apiserver":"kube-apiserver","operation":"list"},"value":0.09156249999999991,"uuid":"7353d0de-dbde-43d8-a98b-217b4d6ddf82","query":"histogram_quantile(0.99,sum(rate(etcd_request_duration_seconds_bucket[2m])) by (le,operation,apiserver)) \u003e 0","metricName":"P99APIEtcdRequestLatency","jobName":"cluster-density"},{"timestamp":"2022-05-26T06:46:39.436Z","labels":{"apiserver":"kube-apiserver","operation":"list"},"value":0.07814285714285717,"uuid":"7353d0de-dbde-43d8-a98b-217b4d6ddf82","query":"histogram_quantile(0.99,sum(rate(etcd_request_duration_seconds_bucket[2m])) by (le,operation,apiserver)) \u003e 0","metricName":"P99APIEtcdRequestLatency","jobName":"cluster-density"},{"timestamp":"2022-05-26T06:44:09.436Z","labels":{"apiserver":"kube-apiserver","operation":"listWithCount"},"value":0.024369620253164557,"uuid":"7353d0de-dbde-43d8-a98b-217b4d6ddf82","query":"histogram_quantile(0.99,sum(rate(etcd_request_duration_seconds_bucket[2m])) by (le,operation,apiserver)) \u003e 0","metricName":"P99APIEtcdRequestLatency","jobName":"cluster-density"},{"timestamp":"2022-05-26T06:44:39.436Z","labels":{"apiserver":"kube-apiserver","operation":"listWithCount"},"value":0.03537557292621542,"uuid":"7353d0de-dbde-43d8-a98b-217b4d6ddf82","query":"histogram_quantile(0.99,sum(rate(etcd_request_duration_seconds_bucket[2m])) by (le,operation,apiserver)) \u003e 0","metricName":"P99APIEtcdRequestLatency","jobName":"cluster-density"},{"timestamp":"2022-05-26T06:45:09.436Z","labels":{"apiserver":"kube-apiserver","operation":"listWithCount"},"value":0.04439241121174866,"uuid":"7353d0de-dbde-43d8-a98b-217b4d6ddf82","query":"histogram_quantile(0.99,sum(rate(etcd_request_duration_seconds_bucket[2m])) by (le,operation,apiserver)) \u003e 0","metricName":"P99APIEtcdRequestLatency","jobName":"cluster-density"},{"timestamp":"2022-05-26T06:45:39.436Z","labels":{"apiserver":"kube-apiserver","operation":"listWithCount"},"value":0.05012499999999932,"uuid":"7353d0de-dbde-43d8-a98b-217b4d6ddf82","query":"histogram_quantile(0.99,sum(rate(etcd_request_duration_seconds_bucket[2m])) by (le,operation,apiserver)) \u003e 0","metricName":"P99APIEtcdRequestLatency","jobName":"cluster-density"},{"timestamp":"2022-05-26T06:46:09.436Z","labels":{"apiserver":"kube-apiserver","operation":"listWithCount"},"value":0.024566013071895425,"uuid":"7353d0de-dbde-43d8-a98b-217b4d6ddf82","query":"histogram_quantile(0.99,sum(rate(etcd_request_duration_seconds_bucket[2m])) by (le,operation,apiserver)) \u003e 0","metricName":"P99APIEtcdRequestLatency","jobName":"cluster-density"},{"timestamp":"2022-05-26T06:46:39.436Z","labels":{"apiserver":"kube-apiserver","operation":"listWithCount"},"value":0.024861349693251537,"uuid":"7353d0de-dbde-43d8-a98b-217b4d6ddf82","query":"histogram_quantile(0.99,sum(rate(etcd_request_duration_seconds_bucket[2m])) by (le,operation,apiserver)) \u003e 0","metricName":"P99APIEtcdRequestLatency","jobName":"cluster-density"},{"timestamp":"2022-05-26T06:44:09.436Z","labels":{"apiserver":"kube-apiserver","operation":"update"},"value":0.024896842105263155,"uuid":"7353d0de-dbde-43d8-a98b-217b4d6ddf82","query":"histogram_quantile(0.99,sum(rate(etcd_request_duration_seconds_bucket[2m])) by (le,operation,apiserver)) \u003e 0","metricName":"P99APIEtcdRequestLatency","jobName":"cluster-density"},{"timestamp":"2022-05-26T06:44:39.436Z","labels":{"apiserver":"kube-apiserver","operation":"update"},"value":0.08639501728052991,"uuid":"7353d0de-dbde-43d8-a98b-217b4d6ddf82","query":"histogram_quantile(0.99,sum(rate(etcd_request_duration_seconds_bucket[2m])) by (le,operation,apiserver)) \u003e 0","metricName":"P99APIEtcdRequestLatency","jobName":"cluster-density"},{"timestamp":"2022-05-26T06:45:09.436Z","labels":{"apiserver":"kube-apiserver","operation":"update"},"value":0.09107252060183782,"uuid":"7353d0de-dbde-43d8-a98b-217b4d6ddf82","query":"histogram_quantile(0.99,sum(rate(etcd_request_duration_seconds_bucket[2m])) by (le,operation,apiserver)) \u003e 0","metricName":"P99APIEtcdRequestLatency","jobName":"cluster-density"},{"timestamp":"2022-05-26T06:45:39.436Z","labels":{"apiserver":"kube-apiserver","operation":"update"},"value":0.09093382352941173,"uuid":"7353d0de-dbde-43d8-a98b-217b4d6ddf82","query":"histogram_quantile(0.99,sum(rate(etcd_request_duration_seconds_bucket[2m])) by (le,operation,apiserver)) \u003e 0","metricName":"P99APIEtcdRequestLatency","jobName":"cluster-density"},{"timestamp":"2022-05-26T06:46:09.436Z","labels":{"apiserver":"kube-apiserver","operation":"update"},"value":0.08451785714285717,"uuid":"7353d0de-dbde-43d8-a98b-217b4d6ddf82","query":"histogram_quantile(0.99,sum(rate(etcd_request_duration_seconds_bucket[2m])) by (le,operation,apiserver)) \u003e 0","metricName":"P99APIEtcdRequestLatency","jobName":"cluster-density"},{"timestamp":"2022-05-26T06:46:39.436Z","labels":{"apiserver":"kube-apiserver","operation":"update"},"value":0.055970588235293994,"uuid":"7353d0de-dbde-43d8-a98b-217b4d6ddf82","query":"histogram_quantile(0.99,sum(rate(etcd_request_duration_seconds_bucket[2m])) by (le,operation,apiserver)) \u003e 0","metricName":"P99APIEtcdRequestLatency","jobName":"cluster-density"},{"timestamp":"2022-05-26T06:44:39.436Z","labels":{"apiserver":"openshift-apiserver","operation":"create"},"value":0.09764284251684321,"uuid":"7353d0de-dbde-43d8-a98b-217b4d6ddf82","query":"histogram_quantile(0.99,sum(rate(etcd_request_duration_seconds_bucket[2m])) by (le,operation,apiserver)) \u003e 0","metricName":"P99APIEtcdRequestLatency","jobName":"cluster-density"},{"timestamp":"2022-05-26T06:45:09.436Z","labels":{"apiserver":"openshift-apiserver","operation":"create"},"value":0.09757140952444443,"uuid":"7353d0de-dbde-43d8-a98b-217b4d6ddf82","query":"histogram_quantile(0.99,sum(rate(etcd_request_duration_seconds_bucket[2m])) by (le,operation,apiserver)) \u003e 0","metricName":"P99APIEtcdRequestLatency","jobName":"cluster-density"},{"timestamp":"2022-05-26T06:45:39.436Z","labels":{"apiserver":"openshift-apiserver","operation":"create"},"value":0.09721429818546595,"uuid":"7353d0de-dbde-43d8-a98b-217b4d6ddf82","query":"histogram_quantile(0.99,sum(rate(etcd_request_duration_seconds_bucket[2m])) by (le,operation,apiserver)) \u003e 0","metricName":"P99APIEtcdRequestLatency","jobName":"cluster-density"},{"timestamp":"2022-05-26T06:46:09.436Z","labels":{"apiserver":"openshift-apiserver","operation":"create"},"value":0.024800000000000003,"uuid":"7353d0de-dbde-43d8-a98b-217b4d6ddf82","query":"histogram_quantile(0.99,sum(rate(etcd_request_duration_seconds_bucket[2m])) by (le,operation,apiserver)) \u003e 0","metricName":"P99APIEtcdRequestLatency","jobName":"cluster-density"},{"timestamp":"2022-05-26T06:46:39.436Z","labels":{"apiserver":"openshift-apiserver","operation":"create"},"value":0.024800000000000003,"uuid":"7353d0de-dbde-43d8-a98b-217b4d6ddf82","query":"histogram_quantile(0.99,sum(rate(etcd_request_duration_seconds_bucket[2m])) by (le,operation,apiserver)) \u003e 0","metricName":"P99APIEtcdRequestLatency","jobName":"cluster-density"},{"timestamp":"2022-05-26T06:44:09.436Z","labels":{"apiserver":"openshift-apiserver","operation":"get"},"value":0.024288888888888895,"uuid":"7353d0de-dbde-43d8-a98b-217b4d6ddf82","query":"histogram_quantile(0.99,sum(rate(etcd_request_duration_seconds_bucket[2m])) by (le,operation,apiserver)) \u003e 0","metricName":"P99APIEtcdRequestLatency","jobName":"cluster-density"},{"timestamp":"2022-05-26T06:44:39.436Z","labels":{"apiserver":"openshift-apiserver","operation":"get"},"value":0.09534999274977671,"uuid":"7353d0de-dbde-43d8-a98b-217b4d6ddf82","query":"histogram_quantile(0.99,sum(rate(etcd_request_duration_seconds_bucket[2m])) by (le,operation,apiserver)) \u003e 0","metricName":"P99APIEtcdRequestLatency","jobName":"cluster-density"},{"timestamp":"2022-05-26T06:45:09.436Z","labels":{"apiserver":"openshift-apiserver","operation":"get"},"value":0.09448748497980922,"uuid":"7353d0de-dbde-43d8-a98b-217b4d6ddf82","query":"histogram_quantile(0.99,sum(rate(etcd_request_duration_seconds_bucket[2m])) by (le,operation,apiserver)) \u003e 0","metricName":"P99APIEtcdRequestLatency","jobName":"cluster-density"},{"timestamp":"2022-05-26T06:45:39.436Z","labels":{"apiserver":"openshift-apiserver","operation":"get"},"value":0.09328411253373634,"uuid":"7353d0de-dbde-43d8-a98b-217b4d6ddf82","query":"histogram_quantile(0.99,sum(rate(etcd_request_duration_seconds_bucket[2m])) by (le,operation,apiserver)) \u003e 0","metricName":"P99APIEtcdRequestLatency","jobName":"cluster-density"},{"timestamp":"2022-05-26T06:46:09.436Z","labels":{"apiserver":"openshift-apiserver","operation":"get"},"value":0.05349959998666647,"uuid":"7353d0de-dbde-43d8-a98b-217b4d6ddf82","query":"histogram_quantile(0.99,sum(rate(etcd_request_duration_seconds_bucket[2m])) by (le,operation,apiserver)) \u003e 0","metricName":"P99APIEtcdRequestLatency","jobName":"cluster-density"},{"timestamp":"2022-05-26T06:46:39.436Z","labels":{"apiserver":"openshift-apiserver","operation":"get"},"value":0.046748716566843936,"uuid":"7353d0de-dbde-43d8-a98b-217b4d6ddf82","query":"histogram_quantile(0.99,sum(rate(etcd_request_duration_seconds_bucket[2m])) by (le,operation,apiserver)) \u003e 0","metricName":"P99APIEtcdRequestLatency","jobName":"cluster-density"},{"timestamp":"2022-05-26T06:44:39.436Z","labels":{"apiserver":"openshift-apiserver","operation":"list"},"value":0.05350177494333522,"uuid":"7353d0de-dbde-43d8-a98b-217b4d6ddf82","query":"histogram_quantile(0.99,sum(rate(etcd_request_duration_seconds_bucket[2m])) by (le,operation,apiserver)) \u003e 0","metricName":"P99APIEtcdRequestLatency","jobName":"cluster-density"},{"timestamp":"2022-05-26T06:45:09.436Z","labels":{"apiserver":"openshift-apiserver","operation":"list"},"value":0.06643791195513582,"uuid":"7353d0de-dbde-43d8-a98b-217b4d6ddf82","query":"histogram_quantile(0.99,sum(rate(etcd_request_duration_seconds_bucket[2m])) by (le,operation,apiserver)) \u003e 0","metricName":"P99APIEtcdRequestLatency","jobName":"cluster-density"},{"timestamp":"2022-05-26T06:45:39.436Z","labels":{"apiserver":"openshift-apiserver","operation":"list"},"value":0.0678572537379768,"uuid":"7353d0de-dbde-43d8-a98b-217b4d6ddf82","query":"histogram_quantile(0.99,sum(rate(etcd_request_duration_seconds_bucket[2m])) by (le,operation,apiserver)) \u003e 0","metricName":"P99APIEtcdRequestLatency","jobName":"cluster-density"},{"timestamp":"2022-05-26T06:46:09.436Z","labels":{"apiserver":"openshift-apiserver","operation":"list"},"value":0.061856903054372935,"uuid":"7353d0de-dbde-43d8-a98b-217b4d6ddf82","query":"histogram_quantile(0.99,sum(rate(etcd_request_duration_seconds_bucket[2m])) by (le,operation,apiserver)) \u003e 0","metricName":"P99APIEtcdRequestLatency","jobName":"cluster-density"},{"timestamp":"2022-05-26T06:46:39.436Z","labels":{"apiserver":"openshift-apiserver","operation":"list"},"value":0.05019880990743722,"uuid":"7353d0de-dbde-43d8-a98b-217b4d6ddf82","query":"histogram_quantile(0.99,sum(rate(etcd_request_duration_seconds_bucket[2m])) by (le,operation,apiserver)) \u003e 0","metricName":"P99APIEtcdRequestLatency","jobName":"cluster-density"},{"timestamp":"2022-05-26T06:44:09.436Z","labels":{"apiserver":"openshift-apiserver","operation":"listWithCount"},"value":0.024557142857142854,"uuid":"7353d0de-dbde-43d8-a98b-217b4d6ddf82","query":"histogram_quantile(0.99,sum(rate(etcd_request_duration_seconds_bucket[2m])) by (le,operation,apiserver)) \u003e 0","metricName":"P99APIEtcdRequestLatency","jobName":"cluster-density"},{"timestamp":"2022-05-26T06:44:39.436Z","labels":{"apiserver":"openshift-apiserver","operation":"listWithCount"},"value":0.02465000239583268,"uuid":"7353d0de-dbde-43d8-a98b-217b4d6ddf82","query":"histogram_quantile(0.99,sum(rate(etcd_request_duration_seconds_bucket[2m])) by (le,operation,apiserver)) \u003e 0","metricName":"P99APIEtcdRequestLatency","jobName":"cluster-density"},{"timestamp":"2022-05-26T06:45:09.436Z","labels":{"apiserver":"openshift-apiserver","operation":"listWithCount"},"value":0.024569235003034005,"uuid":"7353d0de-dbde-43d8-a98b-217b4d6ddf82","query":"histogram_quantile(0.99,sum(rate(etcd_request_duration_seconds_bucket[2m])) by (le,operation,apiserver)) \u003e 0","metricName":"P99APIEtcdRequestLatency","jobName":"cluster-density"},{"timestamp":"2022-05-26T06:45:39.436Z","labels":{"apiserver":"openshift-apiserver","operation":"listWithCount"},"value":0.024422216845099355,"uuid":"7353d0de-dbde-43d8-a98b-217b4d6ddf82","query":"histogram_quantile(0.99,sum(rate(etcd_request_duration_seconds_bucket[2m])) by (le,operation,apiserver)) \u003e 0","metricName":"P99APIEtcdRequestLatency","jobName":"cluster-density"},{"timestamp":"2022-05-26T06:46:09.436Z","labels":{"apiserver":"openshift-apiserver","operation":"listWithCount"},"value":0.024057148435453833,"uuid":"7353d0de-dbde-43d8-a98b-217b4d6ddf82","query":"histogram_quantile(0.99,sum(rate(etcd_request_duration_seconds_bucket[2m])) by (le,operation,apiserver)) \u003e 0","metricName":"P99APIEtcdRequestLatency","jobName":"cluster-density"},{"timestamp":"2022-05-26T06:46:39.436Z","labels":{"apiserver":"openshift-apiserver","operation":"listWithCount"},"value":0.02410002333393828,"uuid":"7353d0de-dbde-43d8-a98b-217b4d6ddf82","query":"histogram_quantile(0.99,sum(rate(etcd_request_duration_seconds_bucket[2m])) by (le,operation,apiserver)) \u003e 0","metricName":"P99APIEtcdRequestLatency","jobName":"cluster-density"},{"timestamp":"2022-05-26T06:44:39.436Z","labels":{"apiserver":"openshift-apiserver","operation":"update"},"value":0.09614289719319186,"uuid":"7353d0de-dbde-43d8-a98b-217b4d6ddf82","query":"histogram_quantile(0.99,sum(rate(etcd_request_duration_seconds_bucket[2m])) by (le,operation,apiserver)) \u003e 0","metricName":"P99APIEtcdRequestLatency","jobName":"cluster-density"},{"timestamp":"2022-05-26T06:45:09.436Z","labels":{"apiserver":"openshift-apiserver","operation":"update"},"value":0.09480007855066797,"uuid":"7353d0de-dbde-43d8-a98b-217b4d6ddf82","query":"histogram_quantile(0.99,sum(rate(etcd_request_duration_seconds_bucket[2m])) by (le,operation,apiserver)) \u003e 0","metricName":"P99APIEtcdRequestLatency","jobName":"cluster-density"},{"timestamp":"2022-05-26T06:45:39.436Z","labels":{"apiserver":"openshift-apiserver","operation":"update"},"value":0.09371872656315106,"uuid":"7353d0de-dbde-43d8-a98b-217b4d6ddf82","query":"histogram_quantile(0.99,sum(rate(etcd_request_duration_seconds_bucket[2m])) by (le,operation,apiserver)) \u003e 0","metricName":"P99APIEtcdRequestLatency","jobName":"cluster-density"},{"timestamp":"2022-05-26T06:46:09.436Z","labels":{"apiserver":"openshift-apiserver","operation":"update"},"value":0.0741247749924995,"uuid":"7353d0de-dbde-43d8-a98b-217b4d6ddf82","query":"histogram_quantile(0.99,sum(rate(etcd_request_duration_seconds_bucket[2m])) by (le,operation,apiserver)) \u003e 0","metricName":"P99APIEtcdRequestLatency","jobName":"cluster-density"},{"timestamp":"2022-05-26T06:46:39.436Z","labels":{"apiserver":"openshift-apiserver","operation":"update"},"value":0.06324935828342154,"uuid":"7353d0de-dbde-43d8-a98b-217b4d6ddf82","query":"histogram_quantile(0.99,sum(rate(etcd_request_duration_seconds_bucket[2m])) by (le,operation,apiserver)) \u003e 0","metricName":"P99APIEtcdRequestLatency","jobName":"cluster-density"}]
